<?xml version="1.0" encoding="utf-8" ?><dwsync><file name="back_arrow_blue.png" server="home276722437.1and1-data.host//rachelmax/" local="3638102815" remote="3638110938" Dst="-1" /><file name="forward_arrow_blue.png" server="home276722437.1and1-data.host//rachelmax/" local="3638102816" remote="3638110939" Dst="-1" /><file name="back_arrow_pink.png" server="home276722437.1and1-data.host//rachelmax/" local="3638102816" remote="3643992830" Dst="-1" /><file name="forward_arrow_pink.png" server="home276722437.1and1-data.host//rachelmax/" local="3638102816" remote="3643992830" Dst="-1" /><file name="back_arrow_blue.png" server="home276722437.1and1-data.host//positivereinforcementpillow/" local="3638102815" remote="3642611097" Dst="-1" /><file name="forward_arrow_blue.png" server="home276722437.1and1-data.host//positivereinforcementpillow/" local="3638102816" remote="3642611099" Dst="-1" /><file name="back_arrow_pink.png" server="home276722437.1and1-data.host//positivereinforcementpillow/" local="3638102816" remote="3642352667" Dst="-1" /><file name="forward_arrow_pink.png" server="home276722437.1and1-data.host//positivereinforcementpillow/" local="3638102816" remote="3642352668" Dst="-1" /><file name="blog_nav_arrows.ai" server="home276722437.1and1-data.host//positivereinforcementpillow/" local="3638102555" remote="3642611098" Dst="-1" /><file name="forward_arrow_black.png" server="home276722437.1and1-data.host//positivereinforcementpillow/" local="3638102815" remote="3642611098" Dst="-1" /><file name="black_arrow_black.png" server="home276722437.1and1-data.host//positivereinforcementpillow/" local="3638102815" remote="3642611099" Dst="-1" /></dwsync>